pooled_ppi/__init__.py
pooled_ppi/sample_pools.py
pooled_ppi-0.1.dist-info/licenses/LICENSE
pooled_ppi-0.1.dist-info/METADATA
pooled_ppi-0.1.dist-info/WHEEL
pooled_ppi-0.1.dist-info/entry_points.txt
pooled_ppi-0.1.dist-info/top_level.txt
pooled_ppi-0.1.dist-info/RECORD
